Eos-0.0.0.dev8.dist-info/DESCRIPTION.rst
Eos-0.0.0.dev8.dist-info/METADATA
Eos-0.0.0.dev8.dist-info/RECORD
Eos-0.0.0.dev8.dist-info/WHEEL
Eos-0.0.0.dev8.dist-info/metadata.json
Eos-0.0.0.dev8.dist-info/top_level.txt
eos/__init__.py
eos/exception.py
eos/holder_filter.py
eos/const/__init__.py
eos/const/eos.py
eos/const/eve.py
eos/data/__init__.py
eos/data/exception.py
eos/data/source.py
eos/data/cache_customizer/__init__.py
eos/data/cache_customizer/customizer.py
eos/data/cache_generator/__init__.py
eos/data/cache_generator/checker.py
eos/data/cache_generator/cleaner.py
eos/data/cache_generator/converter.py
eos/data/cache_generator/generator.py
eos/data/cache_generator/modifier_builder/__init__.py
eos/data/cache_generator/modifier_builder/builder.py
eos/data/cache_generator/modifier_builder/expression_tree/__init__.py
eos/data/cache_generator/modifier_builder/expression_tree/action.py
eos/data/cache_generator/modifier_builder/expression_tree/effect2modifiers.py
eos/data/cache_generator/modifier_builder/expression_tree/etree2actions.py
eos/data/cache_generator/modifier_builder/expression_tree/exception.py
eos/data/cache_generator/modifier_builder/expression_tree/shared.py
eos/data/cache_generator/modifier_builder/modifier_info/__init__.py
eos/data/cache_generator/modifier_builder/modifier_info/exception.py
eos/data/cache_generator/modifier_builder/modifier_info/info2modifiers.py
eos/data/cache_handler/__init__.py
eos/data/cache_handler/abc.py
eos/data/cache_handler/exception.py
eos/data/cache_handler/json_cache_handler.py
eos/data/cache_object/__init__.py
eos/data/cache_object/attribute.py
eos/data/cache_object/effect.py
eos/data/cache_object/modifier.py
eos/data/cache_object/type.py
eos/data/data_handler/__init__.py
eos/data/data_handler/abc.py
eos/data/data_handler/json_data_handler.py
eos/data/data_handler/sqlite_data_handler.py
eos/fit/__init__.py
eos/fit/exception.py
eos/fit/fit.py
eos/fit/tuples.py
eos/fit/attribute_calculator/__init__.py
eos/fit/attribute_calculator/affector.py
eos/fit/attribute_calculator/exception.py
eos/fit/attribute_calculator/map.py
eos/fit/attribute_calculator/register.py
