Metadata-Version: 2.0
Name: Eos
Version: 0.0.0.dev8
Summary: Eos is a fitting engine for for EVE Online.
Home-page: https://github.com/pyfa-org/eos
Author: Pyfa Team
Author-email: UNKNOWN
License: UNKNOWN
Platform: UNKNOWN
Requires-Dist: PyYAML (==3.12)
